Metadata-Version: 2.0
Name: odoo8-addon-l10n-fr-account-fiscal-position-rule
Version: 8.0.0.0.1.99.dev1
Summary: l10n_fr_account_fiscal_position_rule
Home-page: http://www.akretion.com/
Author: Akretion,Odoo Community Association (OCA)
Author-email: support@odoo-community.org
License: AGPL-3
Platform: UNKNOWN
Requires-Dist: odoo (<9.0a,>=8.0a)
Requires-Dist: odoo8-addon-account-fiscal-position-rule
Classifier: Programming Language :: Python :: 2.7
Classifier: Framework :: Odoo
Classifier: License :: OSI Approved :: GNU Affero General Public License v3
